{"type":"FeatureCollection","features":[{"type":"Feature","geometry":{"type":"Point","coordinates":[-75.8166,45.3062]},"properties":{"name":"Dummy","type":"active"}},{"type":"Feature","geometry":{"type":"Point","coordinates":[-75.8166,45.3062]},"properties":{"name":"Poecile atricapillus","type":"active"}},{"type":"Feature","geometry":{"type":"Point","coordinates":[-75.8165,45.3062]},"properties":{"name":"Poecile atricapillus","type":"active"}},{"type":"Feature","geometry":{"type":"Point","coordinates":[-75.8165,45.3062]},"properties":{"name":"Poecile atricapillus","type":"active"}},{"type":"Feature","geometry":{"type":"Point","coordinates":[-75.8164,45.3061]},"properties":{"name":"Poecile atricapillus","type":"active"}}]}