{"type":"FeatureCollection","features":[{"type":"Feature","geometry":{"type":"Point","coordinates":[-78.83,52.99]},"properties":{"ID":"2800","projectID":"248","name":"Wimindji MTL","lastEditedDt":"7/15/2019 10:28:52","status":"2","description":"Site ID:  2800 <br>Landowner ID:  NA Last edited on:  7/15/2019 10:28:52"}},{"type":"Feature","geometry":{"type":"Point","coordinates":[-78.97,51.79]},"properties":{"ID":"2861","projectID":"248","name":"Boatswain Bay","lastEditedDt":"8/14/2019 6:18:07","status":"2","description":"Site ID:  2861 <br>Landowner ID:  NA Last edited on:  8/14/2019 6:18:07"}}]}