{"type":"FeatureCollection","features":[{"type":"Feature","geometry":{"type":"Point","coordinates":[-85.14,41.1]},"properties":{"ID":"2853","projectID":"189","name":"Fort Wayne Children's Zoo","lastEditedDt":"9/25/2019 18:06:11","status":"2","description":"Site ID:  2853 <br>Landowner ID:  NA Last edited on:  9/25/2019 18:06:11"}},{"type":"Feature","geometry":{"type":"Point","coordinates":[-85.82,41.07]},"properties":{"ID":"2854","projectID":"189","name":"Wildwood","lastEditedDt":"9/25/2019 18:06:11","status":"1","description":"Site ID:  2854 <br>Landowner ID:  NA Last edited on:  9/25/2019 18:06:11"}},{"type":"Feature","geometry":{"type":"Point","coordinates":[-85.5,41.22]},"properties":{"ID":"2855","projectID":"189","name":"Dygert","lastEditedDt":"9/25/2019 18:06:11","status":"2","description":"Site ID:  2855 <br>Landowner ID:  NA Last edited on:  9/25/2019 18:06:11"}},{"type":"Feature","geometry":{"type":"Point","coordinates":[-84.86,41.15]},"properties":{"ID":"2856","projectID":"189","name":"Bluecast","lastEditedDt":"9/25/2019 18:06:11","status":"2","description":"Site ID:  2856 <br>Landowner ID:  NA Last edited on:  9/25/2019 18:06:11"}}]}