{"type":"FeatureCollection","features":[{"type":"Feature","geometry":{"type":"Point","coordinates":[-86.34,39.12]},"properties":{"ID":"5305","sensorID":"3156","name":"TC Steele","siteCode":"","dtStart":"2019-06-05 10:30:00.0000000 +00:00","dtEnd":"","fixtureType":"Tower","elevation":"262","comments":"","lastVisitedDt":"2019-06-05","lastEditedDt":"6/12/2019 15:26:38","lastEditedUserID":"15007","siteID":"2753","test":"0","status":"2","countryCode":"US","statprovCode":"US.IN","tsStart":"1559730600","ts.max":"1578945478","tsDiff":"95.8 days","projectID":"264","color":"95.8","description":"Deployment ID:  5305 <br>Sensor ID:  3156 <br>Days since last data:  95.8 <br>Deployment start date:  2019-06-05 10:30:00.0000000 +00:00"}}]}