{"type":"FeatureCollection","features":[{"type":"Feature","geometry":{"type":"Point","coordinates":[10.61,57.74]},"properties":{"ID":"4856","sensorID":"2666","name":"Skagen_2019","siteCode":"","dtStart":"2019-08-24 11:38:00.0000000 +00:00","dtEnd":"2019-11-13 01:00:00.0000000 +00:00","fixtureType":"Tower","elevation":"10","comments":"Omni-directional Antenna ","lastVisitedDt":"2019-11-29","lastEditedDt":"4/14/2020 7:35:26","lastEditedUserID":"2646","siteID":"2595","test":"0","status":"1","countryCode":"DK","statprovCode":"DK.NJ","tsStart":"1566646680","tsEnd":"1573606800","projectID":"216","description":"Deployment ID:  4856 <br>Sensor ID:  2666 <br>Days since last data:  NA <br>Deployment start date:  2019-08-24 11:38:00.0000000 +00:00"}}]}