{"type":"FeatureCollection","features":[{"type":"Feature","geometry":{"type":"Point","coordinates":[-0.26,52.11]},"properties":{"ID":"2461","projectID":"179","name":"RSPB HQ","lastEditedDt":"1/8/2018 12:01:59","status":"2","description":"Site ID:  2461 <br>Landowner ID:  NA Last edited on:  1/8/2018 12:01:59"}}]}