{"type":"FeatureCollection","features":[{"type":"Feature","geometry":{"type":"Point","coordinates":[-85.62,37.9]},"properties":{"ID":"5853","sensorID":"3721","name":"Bernheim Fire Tower","siteCode":"","dtStart":"2019-07-19 00:00:00.0000000 +00:00","dtEnd":"","fixtureType":"Tower","comments":"On the Bernheim Fire Tower ~80 feet AGL.  Plans to add 166MHz omni in 2020 to make it dual mode. 434MHz Yagis are all 15-element Diamond brand.","lastVisitedDt":"2019-12-17","lastEditedDt":"1/14/2020 16:17:25","lastEditedUserID":"13098","siteID":"2959","test":"0","status":"2","countryCode":"US","statprovCode":"US.KY","tsStart":"1563494400","ts.max":"1587123321","tsDiff":" 1.2 days","projectID":"292","color":" 1.2","description":"Deployment ID:  5853 <br>Sensor ID:  3721 <br>Days since last data:  1.2 <br>Deployment start date:  2019-07-19 00:00:00.0000000 +00:00"}},{"type":"Feature","geometry":{"type":"Point","coordinates":[-85.65,37.91]},"properties":{"ID":"5879","sensorID":"3720","name":"Bernheim Education Center","siteCode":"","dtStart":"2019-07-20 00:00:00.0000000 +00:00","dtEnd":"","fixtureType":"Tower","comments":"Station is mounted just outside the education center, and plugged into local power. Data is transmitted over 2G onboard modem. 26 CTT Nodes are placed within the viewshed of the station.","lastVisitedDt":"","lastEditedDt":"1/29/2020 9:30:30","lastEditedUserID":"19829","siteID":"2959","test":"0","status":"2","countryCode":"US","statprovCode":"US.KY","tsStart":"1563580800","ts.max":"1583637989","tsDiff":"41.5 days","projectID":"292","color":"41.5","description":"Deployment ID:  5879 <br>Sensor ID:  3720 <br>Days since last data:  41.5 <br>Deployment start date:  2019-07-20 00:00:00.0000000 +00:00"}},{"type":"Feature","geometry":{"type":"Point","coordinates":[-85.59,37.86]},"properties":{"ID":"5883","sensorID":"3739","name":"Bean House","siteCode":"","dtStart":"2019-07-20 00:00:00.0000000 +00:00","dtEnd":"","fixtureType":"Building","comments":"Mast placed on the roof of the Bean House. Currently four 434MHz Yagi antennas, and one 434MHz omni horizontal loop antenna. Plans to add a 166MHz omni in 2020 to make the station dual-mode.","lastVisitedDt":"","lastEditedDt":"1/14/2020 16:08:34","lastEditedUserID":"13098","siteID":"2959","test":"0","status":"2","countryCode":"US","statprovCode":"US.KY","tsStart":"1563580800","projectID":"292","description":"Deployment ID:  5883 <br>Sensor ID:  3739 <br>Days since last data:  NA <br>Deployment start date:  2019-07-20 00:00:00.0000000 +00:00"}}]}