{"type":"FeatureCollection","features":[{"type":"Feature","geometry":{"type":"Point","coordinates":[-70.54,45.41]},"properties":{"ID":"2815","projectID":"266","name":"Kibby Mountain","lastEditedDt":"7/20/2019 17:56:05","status":"1","description":"Site ID:  2815 <br>Landowner ID:  NA Last edited on:  7/20/2019 17:56:05"}}]}