{"type":"FeatureCollection","features":[{"type":"Feature","geometry":{"type":"Point","coordinates":[16.75,47.77]},"properties":{"ID":"2400","projectID":"121","name":"BSI Dammweg","lastEditedDt":"9/21/2017 7:58:29","status":"2","description":"Site ID:  2400 <br>Landowner ID:  NA Last edited on:  9/21/2017 7:58:29"}}]}