{"type":"FeatureCollection","features":[{"type":"Feature","geometry":{"type":"Point","coordinates":[170.4151,64.6827]},"properties":{"name":"Catharus minimus","type":"active"}},{"type":"Feature","geometry":{"type":"Point","coordinates":[170.3966,64.6774]},"properties":{"name":"Catharus minimus","type":"active"}},{"type":"Feature","geometry":{"type":"Point","coordinates":[170.4028,64.6844]},"properties":{"name":"Catharus minimus","type":"active"}},{"type":"Feature","geometry":{"type":"Point","coordinates":[170.4021,64.681]},"properties":{"name":"Catharus minimus","type":"active"}},{"type":"Feature","geometry":{"type":"Point","coordinates":[170.4021,64.6784]},"properties":{"name":"Catharus minimus","type":"active"}},{"type":"Feature","geometry":{"type":"Point","coordinates":[170.4687,64.6671]},"properties":{"name":"Catharus minimus","type":"active"}},{"type":"Feature","geometry":{"type":"Point","coordinates":[170.3664,64.6909]},"properties":{"name":"Catharus minimus","type":"active"}},{"type":"Feature","geometry":{"type":"Point","coordinates":[170.3966,64.6853]},"properties":{"name":"Catharus minimus","type":"active"}},{"type":"Feature","geometry":{"type":"Point","coordinates":[170.3959,64.6839]},"properties":{"name":"Catharus minimus","type":"active"}},{"type":"Feature","geometry":{"type":"Point","coordinates":[170.3966,64.6838]},"properties":{"name":"Catharus minimus","type":"active"}}]}