{"type":"FeatureCollection","features":[{"type":"Feature","geometry":{"type":"Point","coordinates":[-125.84,49.12]},"properties":{"ID":"4794","sensorID":"2573","name":"Dinner Island","siteCode":"","dtStart":"2018-07-19 20:00:00.0000000 +00:00","dtEnd":"","fixtureType":"PopTower","elevation":" 5","comments":"Deployed 2018/07/19","lastVisitedDt":"2018-07-19","lastEditedDt":"6/24/2019 22:17:16","lastEditedUserID":"3676","siteID":"2565","test":"0","status":"2","countryCode":"CA","statprovCode":"CA.BC","tsStart":"1532030400","ts.max":"1580246609","tsDiff":" 80.7 days","projectID":"191","color":" 80.7","description":"Deployment ID:  4794 <br>Sensor ID:  2573 <br>Days since last data:  80.7 <br>Deployment start date:  2018-07-19 20:00:00.0000000 +00:00"}},{"type":"Feature","geometry":{"type":"Point","coordinates":[-125.67,49.01]},"properties":{"ID":"4795","sensorID":"2576","name":"Kwisitis Visitor Centre, PRNPR","siteCode":"","dtStart":"2018-07-20 19:00:00.0000000 +00:00","dtEnd":"","fixtureType":"Building","elevation":"16","comments":"","lastVisitedDt":"2018-07-20","lastEditedDt":"6/24/2019 22:05:57","lastEditedUserID":"3676","siteID":"2566","test":"0","status":"2","countryCode":"CA","statprovCode":"CA.BC","tsStart":"1532113200","ts.max":"1585841144","tsDiff":" 16.0 days","projectID":"191","color":" 16.0","description":"Deployment ID:  4795 <br>Sensor ID:  2576 <br>Days since last data:  16 <br>Deployment start date:  2018-07-20 19:00:00.0000000 +00:00"}},{"type":"Feature","geometry":{"type":"Point","coordinates":[-125.9,49.12]},"properties":{"ID":"4796","sensorID":"2577","name":"Wickaninnish Inn","siteCode":"","dtStart":"2018-07-20 20:48:00.0000000 +00:00","dtEnd":"","fixtureType":"Building","elevation":"24","comments":"","lastVisitedDt":"2018-07-20","lastEditedDt":"6/24/2019 22:05:57","lastEditedUserID":"3676","siteID":"2567","test":"0","status":"2","countryCode":"CA","statprovCode":"CA.BC","tsStart":"1532119680","ts.max":"1570041260","tsDiff":"198.9 days","projectID":"191","color":"198.9","description":"Deployment ID:  4796 <br>Sensor ID:  2577 <br>Days since last data:  198.9 <br>Deployment start date:  2018-07-20 20:48:00.0000000 +00:00"}},{"type":"Feature","geometry":{"type":"Point","coordinates":[-123.14,49.05]},"properties":{"ID":"5085","sensorID":"2943","name":"Brunswick Point farm","siteCode":"","dtStart":"2019-03-12 22:50:00.0000000 +00:00","dtEnd":"","fixtureType":"PopTower","comments":"","lastVisitedDt":"2019-03-12","lastEditedDt":"6/24/2019 22:05:57","lastEditedUserID":"2476","siteID":"2696","test":"0","status":"2","countryCode":"CA","statprovCode":"CA.BC","tsStart":"1552431000","ts.max":"1586624048","tsDiff":"  6.9 days","projectID":"191","color":"  6.9","description":"Deployment ID:  5085 <br>Sensor ID:  2943 <br>Days since last data:  6.9 <br>Deployment start date:  2019-03-12 22:50:00.0000000 +00:00"}},{"type":"Feature","geometry":{"type":"Point","coordinates":[-123.97,46.98]},"properties":{"ID":"5172","sensorID":"3009","name":"Breckenridge Bluff","siteCode":"","dtStart":"2019-04-13 17:00:00.0000000 +00:00","dtEnd":"","fixtureType":"Tower","comments":"","lastVisitedDt":"2019-04-13","lastEditedDt":"7/30/2019 16:12:10","lastEditedUserID":"2476","siteID":"2718","test":"0","status":"2","countryCode":"US","statprovCode":"US.WA","tsStart":"1555174800","ts.max":"1558393197","tsDiff":"333.7 days","projectID":"191","color":"333.7","description":"Deployment ID:  5172 <br>Sensor ID:  3009 <br>Days since last data:  333.7 <br>Deployment start date:  2019-04-13 17:00:00.0000000 +00:00"}},{"type":"Feature","geometry":{"type":"Point","coordinates":[-123.2,49.21]},"properties":{"ID":"5216","sensorID":"3035","name":"Iona Shore Station","siteCode":"","dtStart":"2019-04-29 18:50:00.0000000 +00:00","dtEnd":"","fixtureType":"Building","comments":"Part of the Ocean Networks Canada station","lastVisitedDt":"2019-04-29","lastEditedDt":"4/29/2019 21:49:12","lastEditedUserID":"2476","siteID":"2722","test":"0","status":"2","countryCode":"CA","statprovCode":"CA.BC","tsStart":"1556563800","ts.max":"1587131459","tsDiff":"  1.1 days","projectID":"191","color":"  1.1","description":"Deployment ID:  5216 <br>Sensor ID:  3035 <br>Days since last data:  1.1 <br>Deployment start date:  2019-04-29 18:50:00.0000000 +00:00"}}]}