{"type":"FeatureCollection","features":[{"type":"Feature","geometry":{"type":"Point","coordinates":[-75.73,45.42]},"properties":{"ID":"2802","projectID":"220","name":"UQO","lastEditedDt":"7/17/2019 12:34:25","status":"2","description":"Site ID:  2802 <br>Landowner ID:  NA Last edited on:  7/17/2019 12:34:25"}}]}