{"type":"FeatureCollection","features":[{"type":"Feature","geometry":{"type":"Point","coordinates":[-71.55,41.21]},"properties":{"ID":"1475","sensorID":"1165","sgID":" 1","name":"BLOCKI-1","siteCode":"BLOCKI-1","dtStart":"2014-09-17 14:14:00.0000000 +00:00","dtEnd":"2014-12-05 00:00:00.0000000 +00:00","landOwnerID":"362","fixtureType":"Tower","comments":"Part of 6-antenna array; all horizontally polarized","lastVisitedDt":"","lastEditedDt":"7/23/2019 14:21:31","lastEditedUserID":"480","siteID":"1893","test":"0","status":"1","countryCode":"US","statprovCode":"US.RI","tsStart":"1410963240","tsEnd":"1417737600","ts.max":"1417736651","tsDiff":"1961.6 days","projectID":"45","color":"1961.6","description":"Deployment ID:  1475 <br>Sensor ID:  1165 <br>Days since last data:  1961.6 <br>Deployment start date:  2014-09-17 14:14:00.0000000 +00:00"}},{"type":"Feature","geometry":{"type":"Point","coordinates":[-71.55,41.21]},"properties":{"ID":"1476","sensorID":"1166","sgID":" 2","name":"BLOCKI-2","siteCode":"BLOCKI-2","dtStart":"2014-09-28 15:24:00.0000000 +00:00","dtEnd":"2014-12-05 00:00:00.0000000 +00:00","landOwnerID":"362","fixtureType":"Tower","comments":"Part of 6-antenna array; all horizontally polarized; port 3 failed on 10/10/2014","lastVisitedDt":"","lastEditedDt":"7/23/2019 14:23:50","lastEditedUserID":"480","siteID":"1895","test":"0","status":"1","countryCode":"US","statprovCode":"US.RI","tsStart":"1411917840","tsEnd":"1417737600","ts.max":"1417736671","tsDiff":"1961.6 days","projectID":"45","color":"1961.6","description":"Deployment ID:  1476 <br>Sensor ID:  1166 <br>Days since last data:  1961.6 <br>Deployment start date:  2014-09-28 15:24:00.0000000 +00:00"}},{"type":"Feature","geometry":{"type":"Point","coordinates":[-71.55,41.21]},"properties":{"ID":"2580","sensorID":"1165","name":"BLOCKI-1","siteCode":"","dtStart":"2015-10-02 03:00:00.0000000 +00:00","dtEnd":"2015-12-05 13:02:00.0000000 +00:00","landOwnerID":"362","fixtureType":"Tower","comments":"On MERL project, but used to track MYWA as well. ","lastVisitedDt":"2015-10-03","lastEditedDt":"7/23/2019 14:21:54","lastEditedUserID":"480","siteID":"1894","test":"0","status":"1","countryCode":"US","statprovCode":"US.RI","tsStart":"1443754800","tsEnd":"1449320520","ts.max":"1449320233","tsDiff":"1596.1 days","projectID":"45","color":"1596.1","description":"Deployment ID:  2580 <br>Sensor ID:  1165 <br>Days since last data:  1596.1 <br>Deployment start date:  2015-10-02 03:00:00.0000000 +00:00"}},{"type":"Feature","geometry":{"type":"Point","coordinates":[-71.55,41.21]},"properties":{"ID":"5443","sensorID":"1165","name":"BLOCKI-1","siteCode":"","dtStart":"2015-10-01 01:00:00.0000000 +00:00","dtEnd":"2015-10-02 02:59:00.0000000 +00:00","fixtureType":"Tower","comments":"","lastVisitedDt":"","lastEditedDt":"7/23/2019 14:35:39","lastEditedUserID":"480","siteID":"1894","test":"0","status":"1","countryCode":"US","statprovCode":"US.RI","tsStart":"1443661200","tsEnd":"1443754740","projectID":"45","description":"Deployment ID:  5443 <br>Sensor ID:  1165 <br>Days since last data:  NA <br>Deployment start date:  2015-10-01 01:00:00.0000000 +00:00"}}]}