{"type":"FeatureCollection","features":[{"type":"Feature","geometry":{"type":"Point","coordinates":[-70.5505,45.4016]},"properties":{"name":"Catharus bicknelli","type":"active"}},{"type":"Feature","geometry":{"type":"Point","coordinates":[-70.5476,45.4003]},"properties":{"name":"Catharus bicknelli","type":"active"}},{"type":"Feature","geometry":{"type":"Point","coordinates":[-70.5443,45.4187]},"properties":{"name":"Catharus bicknelli","type":"active"}},{"type":"Feature","geometry":{"type":"Point","coordinates":[-70.5443,45.4187]},"properties":{"name":"Catharus bicknelli","type":"active"}},{"type":"Feature","geometry":{"type":"Point","coordinates":[-70.5449,45.4226]},"properties":{"name":"Catharus bicknelli","type":"active"}},{"type":"Feature","geometry":{"type":"Point","coordinates":[-70.5683,45.3447]},"properties":{"name":"Catharus bicknelli","type":"active"}},{"type":"Feature","geometry":{"type":"Point","coordinates":[-70.5449,45.4226]},"properties":{"name":"Catharus bicknelli","type":"active"}},{"type":"Feature","geometry":{"type":"Point","coordinates":[-70.548,45.4009]},"properties":{"name":"Catharus bicknelli","type":"active"}}]}