{"type":"FeatureCollection","features":[{"type":"Feature","geometry":{"type":"Point","coordinates":[88.49,47.24]},"properties":{"ID":"2953","projectID":"274","name":"Calumet","lastEditedDt":"12/5/2019 11:21:43","status":"1","description":"Site ID:  2953 <br>Landowner ID:  NA Last edited on:  12/5/2019 11:21:43"}}]}