{"type":"FeatureCollection","features":[{"type":"Feature","geometry":{"type":"Point","coordinates":[16.7661,47.7689]},"properties":{"name":"Sedge Warbler","type":"active"}},{"type":"Feature","geometry":{"type":"Point","coordinates":[16.7661,47.7689]},"properties":{"name":"Eurasian Reed-Warbler","type":"active"}},{"type":"Feature","geometry":{"type":"Point","coordinates":[16.7661,47.7689]},"properties":{"name":"Eurasian Reed-Warbler","type":"active"}},{"type":"Feature","geometry":{"type":"Point","coordinates":[16.7661,47.7689]},"properties":{"name":"Eurasian Reed-Warbler","type":"active"}},{"type":"Feature","geometry":{"type":"Point","coordinates":[16.7661,47.7689]},"properties":{"name":"Eurasian Reed-Warbler","type":"active"}}]}