{"type":"FeatureCollection","features":[{"type":"Feature","geometry":{"type":"Point","coordinates":[-80.5979,42.8216]},"properties":{"name":"Hirundo rustica","type":"active"}},{"type":"Feature","geometry":{"type":"Point","coordinates":[-80.5979,42.8216]},"properties":{"name":"Hirundo rustica","type":"active"}},{"type":"Feature","geometry":{"type":"Point","coordinates":[-80.5979,42.8216]},"properties":{"name":"Hirundo rustica","type":"active"}},{"type":"Feature","geometry":{"type":"Point","coordinates":[-80.5979,42.8216]},"properties":{"name":"Hirundo rustica","type":"active"}},{"type":"Feature","geometry":{"type":"Point","coordinates":[-80.5979,42.8216]},"properties":{"name":"Hirundo rustica","type":"active"}},{"type":"Feature","geometry":{"type":"Point","coordinates":[-80.5979,42.8216]},"properties":{"name":"Hirundo rustica","type":"active"}},{"type":"Feature","geometry":{"type":"Point","coordinates":[-80.6354,43.4412]},"properties":{"name":"Hirundo rustica","type":"active"}},{"type":"Feature","geometry":{"type":"Point","coordinates":[-80.6354,43.4412]},"properties":{"name":"Hirundo rustica","type":"active"}},{"type":"Feature","geometry":{"type":"Point","coordinates":[-80.6354,43.4412]},"properties":{"name":"Hirundo rustica","type":"active"}},{"type":"Feature","geometry":{"type":"Point","coordinates":[-80.6354,43.4412]},"properties":{"name":"Hirundo rustica","type":"active"}},{"type":"Feature","geometry":{"type":"Point","coordinates":[-80.6354,43.4412]},"properties":{"name":"Hirundo rustica","type":"active"}}]}