{"type":"FeatureCollection","features":[{"type":"Feature","geometry":{"type":"Point","coordinates":[-37.35,-4.7]},"properties":{"ID":"2682","projectID":"239","name":"Icapui Shrimp Farm","lastEditedDt":"2/17/2019 13:22:09","status":"2","description":"Site ID:  2682 <br>Landowner ID:  NA Last edited on:  2/17/2019 13:22:09"}},{"type":"Feature","geometry":{"type":"Point","coordinates":[-37.35,-4.68]},"properties":{"ID":"2683","projectID":"239","name":"Icapui Tico's Restaurant","lastEditedDt":"2/17/2019 13:22:09","status":"2","description":"Site ID:  2683 <br>Landowner ID:  NA Last edited on:  2/17/2019 13:22:09"}},{"type":"Feature","geometry":{"type":"Point","coordinates":[-37.11,-4.92]},"properties":{"ID":"2684","projectID":"239","name":"Areia Branca BCCB","lastEditedDt":"2/17/2019 13:22:09","status":"2","description":"Site ID:  2684 <br>Landowner ID:  NA Last edited on:  2/17/2019 13:22:09"}}]}