{"type":"FeatureCollection","features":[{"type":"Feature","geometry":{"type":"Point","coordinates":[120.23,-20.54]},"properties":{"ID":"2728","projectID":"235","name":"Yarrie","lastEditedDt":"5/1/2019 18:19:13","status":"2","description":"Site ID:  2728 <br>Landowner ID:  NA Last edited on:  5/1/2019 18:19:13"}},{"type":"Feature","geometry":{"type":"Point","coordinates":[119.22,-22.61]},"properties":{"ID":"2791","projectID":"235","name":"Marillana","lastEditedDt":"7/8/2019 22:59:57","status":"2","description":"Site ID:  2791 <br>Landowner ID:  NA Last edited on:  7/8/2019 22:59:57"}},{"type":"Feature","geometry":{"type":"Point","coordinates":[118.81,-23.05]},"properties":{"ID":"2911","projectID":"235","name":"Area C","lastEditedDt":"9/26/2019 0:56:22","status":"2","description":"Site ID:  2911 <br>Landowner ID:  NA Last edited on:  9/26/2019 0:56:22"}},{"type":"Feature","geometry":{"type":"Point","coordinates":[119.6,-23.43]},"properties":{"ID":"2957","projectID":"235","name":"Coombanbunna","lastEditedDt":"12/9/2019 21:47:06","status":"2","description":"Site ID:  2957 <br>Landowner ID:  NA Last edited on:  12/9/2019 21:47:06"}}]}