{"type":"FeatureCollection","features":[{"type":"Feature","geometry":{"type":"Point","coordinates":[-93.23,47.19]},"properties":{"ID":"2740","projectID":"256","name":"Blandin","lastEditedDt":"5/18/2019 8:17:05","status":"2","description":"Site ID:  2740 <br>Landowner ID:  NA Last edited on:  5/18/2019 8:17:05"}}]}