{"type":"FeatureCollection","features":[{"type":"Feature","geometry":{"type":"Point","coordinates":[-81.43,30.44]},"properties":{"ID":"5254","sensorID":"3081","name":"Kingsley Plantation","siteCode":"","dtStart":"2019-04-08 18:00:00.0000000 +00:00","dtEnd":"","fixtureType":"PopTower","elevation":"1","comments":"","lastVisitedDt":"2019-04-09","lastEditedDt":"5/15/2019 12:00:54","lastEditedUserID":"351","siteID":"2737","test":"0","status":"2","countryCode":"US","statprovCode":"US.FL","tsStart":"1554746400","ts.max":"1578769828","tsDiff":"97.8 days","projectID":"257","color":"97.8","description":"Deployment ID:  5254 <br>Sensor ID:  3081 <br>Days since last data:  97.8 <br>Deployment start date:  2019-04-08 18:00:00.0000000 +00:00"}}]}