{"type":"FeatureCollection","features":[{"type":"Feature","geometry":{"type":"Point","coordinates":[-79.8,43.29]},"properties":{"ID":"5027","sensorID":"2864","name":"CCIW","siteCode":"","dtStart":"2018-12-05 17:00:00.0000000 +00:00","dtEnd":"","fixtureType":"Tower","elevation":"75","comments":"Tower on the roof of the Canada Centre for Inland Waters, using a Non-Penetrating Roof Mount","lastVisitedDt":"2018-12-05","lastEditedDt":"6/24/2019 22:05:57","lastEditedUserID":"2672","siteID":"2666","test":"0","status":"2","countryCode":"CA","statprovCode":"CA.ON","tsStart":"1544029200","ts.max":"1579106341","tsDiff":" 93.9 days","projectID":"231","color":" 93.9","description":"Deployment ID:  5027 <br>Sensor ID:  2864 <br>Days since last data:  93.9 <br>Deployment start date:  2018-12-05 17:00:00.0000000 +00:00"}},{"type":"Feature","geometry":{"type":"Point","coordinates":[-80.25,43.6]},"properties":{"ID":"5074","sensorID":"2927","name":"Guelph Lake 2","siteCode":"","dtStart":"2019-02-14 16:00:00.0000000 +00:00","dtEnd":"2019-05-06 00:00:00.0000000 +00:00","fixtureType":"PopTower","comments":"Future Site of new Guelph Lake Nature Centre","lastVisitedDt":"2019-05-06","lastEditedDt":"8/19/2019 8:14:06","lastEditedUserID":"2672","siteID":"2690","test":"0","status":"1","countryCode":"CA","statprovCode":"CA.ON","tsStart":"1550160000","tsEnd":"1557100800","ts.max":"1556283223","tsDiff":"358.1 days","projectID":"231","color":"358.1","description":"Deployment ID:  5074 <br>Sensor ID:  2927 <br>Days since last data:  358.1 <br>Deployment start date:  2019-02-14 16:00:00.0000000 +00:00"}},{"type":"Feature","geometry":{"type":"Point","coordinates":[-80.26,43.59]},"properties":{"ID":"5075","sensorID":"2928","name":"Guelph Lake Nature Centre","siteCode":"","dtStart":"2019-02-15 12:00:00.0000000 +00:00","dtEnd":"2019-05-06 00:00:00.0000000 +00:00","fixtureType":"Unknown","comments":"Sensorgnome attached to antenna near feeders","lastVisitedDt":"2019-05-06","lastEditedDt":"8/19/2019 8:13:05","lastEditedUserID":"2672","siteID":"2691","test":"0","status":"1","countryCode":"CA","statprovCode":"CA.ON","tsStart":"1550232000","tsEnd":"1557100800","ts.max":"1557065299","tsDiff":"349.0 days","projectID":"231","color":"349.0","description":"Deployment ID:  5075 <br>Sensor ID:  2928 <br>Days since last data:  349 <br>Deployment start date:  2019-02-15 12:00:00.0000000 +00:00"}},{"type":"Feature","geometry":{"type":"Point","coordinates":[-80.26,43.59]},"properties":{"ID":"5858","sensorID":"3404","name":"Guelph Lake Nature Centre","siteCode":"","dtStart":"2019-12-20 12:00:00.0000000 +00:00","dtEnd":"","fixtureType":"Unknown","comments":"4ft Whip Antenna","lastVisitedDt":"2019-12-20","lastEditedDt":"12/20/2019 9:17:44","lastEditedUserID":"2672","siteID":"2691","test":"0","status":"2","countryCode":"CA","statprovCode":"CA.ON","tsStart":"1576843200","ts.max":"1583501462","tsDiff":" 43.1 days","projectID":"231","color":" 43.1","description":"Deployment ID:  5858 <br>Sensor ID:  3404 <br>Days since last data:  43.1 <br>Deployment start date:  2019-12-20 12:00:00.0000000 +00:00"}}]}