{"type":"FeatureCollection","features":[{"type":"Feature","geometry":{"type":"Point","coordinates":[-72.54,41.25]},"properties":{"ID":"2198","projectID":"84","name":"HAMMO","lastEditedDt":"8/14/2017 17:26:36","status":"1","description":"Site ID:  2198 <br>Landowner ID:  NA Last edited on:  8/14/2017 17:26:36"}},{"type":"Feature","geometry":{"type":"Point","coordinates":[-72.54,41.25]},"properties":{"ID":"2199","projectID":"84","name":"Hammonasset State Pa","lastEditedDt":"8/14/2017 17:26:36","status":"2","description":"Site ID:  2199 <br>Landowner ID:  NA Last edited on:  8/14/2017 17:26:36"}},{"type":"Feature","geometry":{"type":"Point","coordinates":[-73.1,41.15]},"properties":{"ID":"2200","projectID":"84","name":"Stratford Point","lastEditedDt":"8/14/2017 17:26:36","status":"2","description":"Site ID:  2200 <br>Landowner ID:  NA Last edited on:  8/14/2017 17:26:36"}},{"type":"Feature","geometry":{"type":"Point","coordinates":[-73.1,41.15]},"properties":{"ID":"2201","projectID":"84","name":"StratfordPt","lastEditedDt":"8/14/2017 17:26:36","status":"1","description":"Site ID:  2201 <br>Landowner ID:  NA Last edited on:  8/14/2017 17:26:36"}}]}