{"type":"FeatureCollection","features":[{"type":"Feature","geometry":{"type":"Point","coordinates":[-65.0548,44.4166]},"properties":{"name":"","type":"pending"}},{"type":"Feature","geometry":{"type":"Point","coordinates":[-65.0548,44.4166]},"properties":{"name":"Chaetura pelagica","type":"active"}}]}