{"type":"FeatureCollection","features":[{"type":"Feature","geometry":{"type":"Point","coordinates":[-80.146,43.319]},"properties":{"name":"Myotis leibii","type":"active"}},{"type":"Feature","geometry":{"type":"Point","coordinates":[-80.2907,43.2985]},"properties":{"name":"Myotis lucifugus","type":"active"}},{"type":"Feature","geometry":{"type":"Point","coordinates":[-80.2907,43.2985]},"properties":{"name":"Myotis lucifugus","type":"active"}},{"type":"Feature","geometry":{"type":"Point","coordinates":[-80.2907,43.2985]},"properties":{"name":"Myotis lucifugus","type":"active"}},{"type":"Feature","geometry":{"type":"Point","coordinates":[-80.2907,43.2985]},"properties":{"name":"Myotis lucifugus","type":"active"}},{"type":"Feature","geometry":{"type":"Point","coordinates":[-80.2907,43.2985]},"properties":{"name":"Myotis lucifugus","type":"active"}},{"type":"Feature","geometry":{"type":"Point","coordinates":[-80.2907,43.2985]},"properties":{"name":"Myotis lucifugus","type":"active"}},{"type":"Feature","geometry":{"type":"Point","coordinates":[-80.2907,43.2985]},"properties":{"name":"Myotis lucifugus","type":"active"}},{"type":"Feature","geometry":{"type":"Point","coordinates":[-80.2907,42.2985]},"properties":{"name":"Myotis lucifugus","type":"active"}},{"type":"Feature","geometry":{"type":"Point","coordinates":[-80.2907,43.2985]},"properties":{"name":"Myotis lucifugus","type":"active"}},{"type":"Feature","geometry":{"type":"Point","coordinates":[-80.2907,43.2985]},"properties":{"name":"Myotis lucifugus","type":"active"}},{"type":"Feature","geometry":{"type":"Point","coordinates":[-80.2907,43.2985]},"properties":{"name":"Myotis lucifugus","type":"active"}},{"type":"Feature","geometry":{"type":"Point","coordinates":[-80.2907,43.2985]},"properties":{"name":"Myotis lucifugus","type":"active"}},{"type":"Feature","geometry":{"type":"Point","coordinates":[-80.2907,43.2985]},"properties":{"name":"Myotis lucifugus","type":"active"}},{"type":"Feature","geometry":{"type":"Point","coordinates":[-80.2907,43.2985]},"properties":{"name":"Myotis lucifugus","type":"active"}},{"type":"Feature","geometry":{"type":"Point","coordinates":[-80.2907,43.2985]},"properties":{"name":"Myotis lucifugus","type":"active"}},{"type":"Feature","geometry":{"type":"Point","coordinates":[-80.2907,43.2985]},"properties":{"name":"Myotis lucifugus","type":"active"}},{"type":"Feature","geometry":{"type":"Point","coordinates":[-80.2907,43.2985]},"properties":{"name":"Myotis lucifugus","type":"active"}},{"type":"Feature","geometry":{"type":"Point","coordinates":[-80.2907,43.2985]},"properties":{"name":"Myotis lucifugus","type":"active"}},{"type":"Feature","geometry":{"type":"Point","coordinates":[-80.2907,43.2985]},"properties":{"name":"Myotis lucifugus","type":"active"}}]}