{"type":"FeatureCollection","features":[{"type":"Feature","geometry":{"type":"Point","coordinates":[-81.618,45.2475]},"properties":{"name":"Anax junius","type":"active"}},{"type":"Feature","geometry":{"type":"Point","coordinates":[-81.618,45.2475]},"properties":{"name":"Anax junius","type":"active"}},{"type":"Feature","geometry":{"type":"Point","coordinates":[-81.618,45.2475]},"properties":{"name":"Anax junius","type":"active"}},{"type":"Feature","geometry":{"type":"Point","coordinates":[-81.618,45.2475]},"properties":{"name":"Anax junius","type":"active"}},{"type":"Feature","geometry":{"type":"Point","coordinates":[-81.618,45.2475]},"properties":{"name":"Anax junius","type":"active"}},{"type":"Feature","geometry":{"type":"Point","coordinates":[-81.618,45.2475]},"properties":{"name":"Anax junius","type":"active"}},{"type":"Feature","geometry":{"type":"Point","coordinates":[-81.618,45.2475]},"properties":{"name":"Anax junius","type":"active"}},{"type":"Feature","geometry":{"type":"Point","coordinates":[-81.618,45.2475]},"properties":{"name":"Anax junius","type":"active"}},{"type":"Feature","geometry":{"type":"Point","coordinates":[-81.618,45.2475]},"properties":{"name":"Anax junius","type":"active"}},{"type":"Feature","geometry":{"type":"Point","coordinates":[-81.618,45.2475]},"properties":{"name":"Anax junius","type":"active"}}]}