{"type":"FeatureCollection","features":[{"type":"Feature","geometry":{"type":"Point","coordinates":[-77.72,40.95]},"properties":{"ID":"2584","projectID":"134","landOwnerID":"6165","name":"State Game Lands Curtin Road","lastEditedDt":"9/20/2018 19:25:51","status":"2","description":"Site ID:  2584 <br>Landowner ID:  6165 Last edited on:  9/20/2018 19:25:51"}},{"type":"Feature","geometry":{"type":"Point","coordinates":[-77.61,41.05]},"properties":{"ID":"2585","projectID":"134","landOwnerID":"6166","name":"Foster Joseph Sayers Dam","lastEditedDt":"9/20/2018 19:25:51","status":"2","description":"Site ID:  2585 <br>Landowner ID:  6166 Last edited on:  9/20/2018 19:25:51"}},{"type":"Feature","geometry":{"type":"Point","coordinates":[-77.7,40.98]},"properties":{"ID":"2586","projectID":"134","landOwnerID":"6165","name":"Howard Nursey","lastEditedDt":"9/20/2018 19:25:51","status":"2","description":"Site ID:  2586 <br>Landowner ID:  6165 Last edited on:  9/20/2018 19:25:51"}},{"type":"Feature","geometry":{"type":"Point","coordinates":[-77.68,40.99]},"properties":{"ID":"2626","projectID":"134","landOwnerID":"6165","name":"323 Lamb's Gap","lastEditedDt":"9/20/2018 19:25:51","status":"2","description":"Site ID:  2626 <br>Landowner ID:  6165 Last edited on:  9/20/2018 19:25:51"}}]}