{"type":"FeatureCollection","features":[{"type":"Feature","geometry":{"type":"Point","coordinates":[-71.23,48.21]},"properties":{"ID":"2348","projectID":"159","name":"FE-100-1","lastEditedDt":"8/14/2017 17:26:36","status":"1","description":"Site ID:  2348 <br>Landowner ID:  NA Last edited on:  8/14/2017 17:26:36"}},{"type":"Feature","geometry":{"type":"Point","coordinates":[-71.22,48.2]},"properties":{"ID":"2349","projectID":"159","name":"FE-100-3","lastEditedDt":"8/14/2017 17:26:36","status":"1","description":"Site ID:  2349 <br>Landowner ID:  NA Last edited on:  8/14/2017 17:26:36"}},{"type":"Feature","geometry":{"type":"Point","coordinates":[-71.21,48.2]},"properties":{"ID":"2350","projectID":"159","name":"FE-170","lastEditedDt":"8/14/2017 17:26:36","status":"1","description":"Site ID:  2350 <br>Landowner ID:  NA Last edited on:  8/14/2017 17:26:36"}},{"type":"Feature","geometry":{"type":"Point","coordinates":[-71.25,48.24]},"properties":{"ID":"2380","projectID":"159","name":"FERS","lastEditedDt":"8/25/2017 15:41:20","status":"2","description":"Site ID:  2380 <br>Landowner ID:  NA Last edited on:  8/25/2017 15:41:20"}}]}