{"type":"FeatureCollection","features":[{"type":"Feature","geometry":{"type":"Point","coordinates":[-71.87,41.33]},"properties":{"ID":"3945","sensorID":"2088","name":"Barn Island","siteCode":"","dtStart":"2017-04-18 20:00:00.0000000 +00:00","dtEnd":"","fixtureType":"Tower","elevation":" 3","comments":"","lastVisitedDt":"2017-04-26","lastEditedDt":"6/24/2019 22:05:57","lastEditedUserID":" 545","siteID":"2304","test":"0","status":"2","utcOffset":"-5","countryCode":"US","statprovCode":"US.CT","tsStart":"1492545600","projectID":"143","description":"Deployment ID:  3945 <br>Sensor ID:  2088 <br>Days since last data:  NA <br>Deployment start date:  2017-04-18 20:00:00.0000000 +00:00"}},{"type":"Feature","geometry":{"type":"Point","coordinates":[-72.66,41.27]},"properties":{"ID":"3946","sensorID":"2088","name":"Guilford","siteCode":"","dtStart":"2017-04-18 20:00:00.0000000 +00:00","dtEnd":"","fixtureType":"Tower","elevation":" 4","comments":"","lastVisitedDt":"2017-04-18","lastEditedDt":"6/24/2019 22:05:57","lastEditedUserID":" 545","siteID":"2305","test":"0","status":"2","utcOffset":"-5","countryCode":"US","statprovCode":"US.CT","tsStart":"1492545600","projectID":"143","description":"Deployment ID:  3946 <br>Sensor ID:  2088 <br>Days since last data:  NA <br>Deployment start date:  2017-04-18 20:00:00.0000000 +00:00"}},{"type":"Feature","geometry":{"type":"Point","coordinates":[-72.66,41.27]},"properties":{"ID":"3964","sensorID":"2091","name":"Guilford","siteCode":"","dtStart":"2017-04-18 20:00:00.0000000 +00:00","dtEnd":"","fixtureType":"Existing","elevation":" 3","comments":"","lastVisitedDt":"2017-05-02","lastEditedDt":"6/24/2019 22:05:57","lastEditedUserID":" 545","siteID":"2305","test":"0","status":"2","utcOffset":"-5","countryCode":"US","statprovCode":"US.CT","tsStart":"1492545600","projectID":"143","description":"Deployment ID:  3964 <br>Sensor ID:  2091 <br>Days since last data:  NA <br>Deployment start date:  2017-04-18 20:00:00.0000000 +00:00"}},{"type":"Feature","geometry":{"type":"Point","coordinates":[-73.33,41.11]},"properties":{"ID":"4125","sensorID":"2171","name":"Sherwood","siteCode":"","dtStart":"2017-06-28 20:00:00.0000000 +00:00","dtEnd":"","fixtureType":"Tower","elevation":" 0","comments":"","lastVisitedDt":"2017-06-29","lastEditedDt":"6/24/2019 22:05:57","lastEditedUserID":"2435","siteID":"2307","test":"0","status":"2","utcOffset":"-5","countryCode":"US","statprovCode":"US.CT","tsStart":"1498680000","projectID":"143","description":"Deployment ID:  4125 <br>Sensor ID:  2171 <br>Days since last data:  NA <br>Deployment start date:  2017-06-28 20:00:00.0000000 +00:00"}},{"type":"Feature","geometry":{"type":"Point","coordinates":[-72.06,41.18]},"properties":{"ID":"4194","sensorID":"2204","name":"Harkness","siteCode":"","dtStart":"2017-08-08 20:00:00.0000000 +00:00","dtEnd":"","fixtureType":"Building","elevation":"15","comments":"","lastVisitedDt":"2017-08-10","lastEditedDt":"6/24/2019 22:17:56","lastEditedUserID":"2435","siteID":"2306","test":"0","status":"2","utcOffset":"-5","countryCode":"US","statprovCode":"US.CT","tsStart":"1502222400","projectID":"143","description":"Deployment ID:  4194 <br>Sensor ID:  2204 <br>Days since last data:  NA <br>Deployment start date:  2017-08-08 20:00:00.0000000 +00:00"}}]}