{"type":"FeatureCollection","features":[{"type":"Feature","geometry":{"type":"Point","coordinates":[-80.09,32.61]},"properties":{"ID":"3049","sensorID":"1662","name":"Kiawah Island Club - SALS 2016","siteCode":"","dtStart":"2016-05-04 13:34:00.0000000 +00:00","dtEnd":"2016-06-06 07:57:00.0000000 +00:00","landOwnerID":"594","fixtureType":"PopTower","comments":"","lastVisitedDt":"2016-05-05","lastEditedDt":"6/24/2019 22:05:57","lastEditedUserID":"351","siteID":"1814","test":"0","status":"1","countryCode":"US","statprovCode":"US.SC","tsStart":"1462368840","tsEnd":"1465199820","ts.max":"1465194293","tsDiff":"1412.4 days","projectID":"29","color":"1412.4","description":"Deployment ID:  3049 <br>Sensor ID:  1662 <br>Days since last data:  1412.4 <br>Deployment start date:  2016-05-04 13:34:00.0000000 +00:00"}},{"type":"Feature","geometry":{"type":"Point","coordinates":[-80.09,32.61]},"properties":{"ID":"4983","sensorID":"1662","name":"Kiawah Island Club - SALS 2016","siteCode":"","dtStart":"2016-05-04 13:00:00.0000000 +00:00","dtEnd":"2016-05-04 13:34:00.0000000 +00:00","fixtureType":"PopTower","comments":"","lastVisitedDt":"","lastEditedDt":"6/24/2019 22:05:57","lastEditedUserID":"351","siteID":"1814","test":"1","status":"1","countryCode":"US","statprovCode":"US.SC","tsStart":"1462366800","tsEnd":"1462368840","ts.max":"1462368327","tsDiff":"1445.1 days","projectID":"29","color":"1445.1","description":"Deployment ID:  4983 <br>Sensor ID:  1662 <br>Days since last data:  1445.1 <br>Deployment start date:  2016-05-04 13:00:00.0000000 +00:00"}}]}