{"type":"FeatureCollection","features":[{"type":"Feature","geometry":{"type":"Point","coordinates":[-66.54,47.19]},"properties":{"ID":"2078","projectID":"72","name":"HR Summer Deployment","lastEditedDt":"8/14/2017 17:26:36","status":"1","description":"Site ID:  2078 <br>Landowner ID:  NA Last edited on:  8/14/2017 17:26:36"}},{"type":"Feature","geometry":{"type":"Point","coordinates":[-66.55,47.2]},"properties":{"ID":"2079","projectID":"72","name":"HR Summer Deployment","lastEditedDt":"8/14/2017 17:26:36","status":"1","description":"Site ID:  2079 <br>Landowner ID:  NA Last edited on:  8/14/2017 17:26:36"}},{"type":"Feature","geometry":{"type":"Point","coordinates":[-66.55,47.2]},"properties":{"ID":"2080","projectID":"72","name":"Migration Fall Deplo","lastEditedDt":"8/14/2017 17:26:36","status":"1","description":"Site ID:  2080 <br>Landowner ID:  NA Last edited on:  8/14/2017 17:26:36"}},{"type":"Feature","geometry":{"type":"Point","coordinates":[-66.55,47.2]},"properties":{"ID":"2081","projectID":"72","name":"NBBITH1","lastEditedDt":"8/14/2017 17:26:36","status":"1","description":"Site ID:  2081 <br>Landowner ID:  NA Last edited on:  8/14/2017 17:26:36"}},{"type":"Feature","geometry":{"type":"Point","coordinates":[-66.54,47.21]},"properties":{"ID":"2082","projectID":"72","name":"NBBITH2","lastEditedDt":"8/14/2017 17:26:36","status":"1","description":"Site ID:  2082 <br>Landowner ID:  NA Last edited on:  8/14/2017 17:26:36"}}]}