{"type":"FeatureCollection","features":[{"type":"Feature","geometry":{"type":"Point","coordinates":[-89.97,29.25]},"properties":{"ID":"4047","sensorID":"2138","name":"Exxon Fields","siteCode":"","dtStart":"2017-02-21 07:00:00.0000000 +00:00","dtEnd":"","fixtureType":"PopTower","elevation":"1","comments":"","lastVisitedDt":"2017-05-18","lastEditedDt":"6/24/2019 22:17:56","lastEditedUserID":"652","siteID":"2299","test":"0","status":"2","utcOffset":"-5","countryCode":"US","statprovCode":"US.LA","tsStart":"1487660400","projectID":"132","description":"Deployment ID:  4047 <br>Sensor ID:  2138 <br>Days since last data:  NA <br>Deployment start date:  2017-02-21 07:00:00.0000000 +00:00"}}]}